docs/Makefile
docs/source/conf.py
docs/source/index.rst
docs/source/modules.rst
docs/source/phir.rst
phir/__init__.py
phir/cli.py
phir/model.py
phir/py.typed
tests/cond_barrier_qparallel.json
tests/example.json
tests/test_model.py
phir-0.3.3.dist-info/LICENSE
phir-0.3.3.dist-info/METADATA
phir-0.3.3.dist-info/WHEEL
phir-0.3.3.dist-info/entry_points.txt
phir-0.3.3.dist-info/top_level.txt
phir-0.3.3.dist-info/RECORD
