Metadata-Version: 2.1
Name: phir
Version: 0.3.3
Summary: A data model and validation tool for PHIR (PECOS High-level Intermediate Representation).
Author-email: Kartik Singhal <kartik.singhal@quantinuum.com>, Ciarán Ryan-Anderson <ciaran.ryan-anderson@quantinuum.com>
License: BSD 3-Clause License
Project-URL: Changelog, https://github.com/CQCL/phir/blob/main/CHANGELOG.md
Project-URL: Documentation, https://cqcl.github.io/phir/
Project-URL: Repository, https://github.com/CQCL/phir
Classifier: Environment :: Console
Classifier: Intended Audience :: Developers
Classifier: Intended Audience :: Science/Research
Classifier: License :: OSI Approved :: BSD License
Classifier: Operating System :: OS Independent
Classifier: Programming Language :: Python :: 3
Classifier: Topic :: Scientific/Engineering
Classifier: Topic :: Software Development :: Libraries :: Python Modules
Classifier: Typing :: Typed
Requires-Python: >=3.10
License-File: LICENSE
Requires-Dist: pydantic
Requires-Dist: rich
Provides-Extra: docs
Requires-Dist: autodoc-pydantic ; extra == 'docs'
Requires-Dist: pydata-sphinx-theme ; extra == 'docs'
Requires-Dist: sphinx ; extra == 'docs'
Provides-Extra: tests
Requires-Dist: pytest ; extra == 'tests'
